{
  "_format": "hh-sol-cache-2",
  "files": {
    "/Users/admin/social-points/contracts/Game.sol": {
      "lastModificationDate": 1730208640221,
      "contentHash": "21bd3432fb0bc29489e594f758889f51",
      "sourceName": "contracts/Game.sol",
      "solcConfig": {
        "version": "0.8.22",
        "settings": {
          "optimizer": {
            "enabled": true,
            "runs": 200
          },
          "viaIR": true,
          "evmVersion": "paris",
          "outputSelection": {
            "*": {
              "*": [
                "abi",
                "evm.bytecode",
                "evm.deployedBytecode",
                "evm.methodIdentifiers",
                "metadata",
                "storageLayout"
              ],
              "": [
                "ast"
              ]
            }
          }
        }
      },
      "imports": [
        "./storage/GameStorage.sol",
        "./libraries/GameLibrary.sol",
        "./libraries/GameTypes.sol",
        "@openzeppelin/contracts-upgradeable/proxy/utils/UUPSUpgradeable.sol",
        "@openzeppelin/contracts-upgradeable/access/OwnableUpgradeable.sol"
      ],
      "versionPragmas": [
        "^0.8.22"
      ],
      "artifacts": [
        "Game"
      ]
    },
    "/Users/admin/social-points/contracts/PlayerManager.sol": {
      "lastModificationDate": 1730107941411,
      "contentHash": "d13451de2ed445dce75975f30a5f2c36",
      "sourceName": "contracts/PlayerManager.sol",
      "solcConfig": {
        "version": "0.8.22",
        "settings": {
          "optimizer": {
            "enabled": true,
            "runs": 200
          },
          "viaIR": true,
          "evmVersion": "paris",
          "outputSelection": {
            "*": {
              "*": [
                "abi",
                "evm.bytecode",
                "evm.deployedBytecode",
                "evm.methodIdentifiers",
                "metadata",
                "storageLayout"
              ],
              "": [
                "ast"
              ]
            }
          }
        }
      },
      "imports": [
        "@openzeppelin/contracts-upgradeable/proxy/utils/Initializable.sol",
        "@openzeppelin/contracts-upgradeable/access/OwnableUpgradeable.sol",
        "@openzeppelin/contracts-upgradeable/proxy/utils/UUPSUpgradeable.sol",
        "./PlayerScoring.sol"
      ],
      "versionPragmas": [
        "^0.8.22"
      ],
      "artifacts": [
        "PlayerManager"
      ]
    },
    "/Users/admin/social-points/contracts/PointsCalculator.sol": {
      "lastModificationDate": 1730107559942,
      "contentHash": "40044b7180919bafc8e56c7f69785abc",
      "sourceName": "contracts/PointsCalculator.sol",
      "solcConfig": {
        "version": "0.8.22",
        "settings": {
          "optimizer": {
            "enabled": true,
            "runs": 200
          },
          "viaIR": true,
          "evmVersion": "paris",
          "outputSelection": {
            "*": {
              "*": [
                "abi",
                "evm.bytecode",
                "evm.deployedBytecode",
                "evm.methodIdentifiers",
                "metadata",
                "storageLayout"
              ],
              "": [
                "ast"
              ]
            }
          }
        }
      },
      "imports": [
        "@openzeppelin/contracts-upgradeable/proxy/utils/Initializable.sol",
        "@openzeppelin/contracts-upgradeable/access/OwnableUpgradeable.sol",
        "@openzeppelin/contracts-upgradeable/proxy/utils/UUPSUpgradeable.sol",
        "./PlayerManager.sol",
        "./PointsRules.sol"
      ],
      "versionPragmas": [
        "^0.8.22"
      ],
      "artifacts": [
        "PointsCalculator"
      ]
    },
    "/Users/admin/social-points/contracts/PrizeDistributor.sol": {
      "lastModificationDate": 1730107566972,
      "contentHash": "3e4ffc81e08ed4ad11dbd423df04fd1d",
      "sourceName": "contracts/PrizeDistributor.sol",
      "solcConfig": {
        "version": "0.8.22",
        "settings": {
          "optimizer": {
            "enabled": true,
            "runs": 200
          },
          "viaIR": true,
          "evmVersion": "paris",
          "outputSelection": {
            "*": {
              "*": [
                "abi",
                "evm.bytecode",
                "evm.deployedBytecode",
                "evm.methodIdentifiers",
                "metadata",
                "storageLayout"
              ],
              "": [
                "ast"
              ]
            }
          }
        }
      },
      "imports": [
        "@openzeppelin/contracts-upgradeable/proxy/utils/Initializable.sol",
        "@openzeppelin/contracts-upgradeable/access/OwnableUpgradeable.sol",
        "@openzeppelin/contracts-upgradeable/proxy/utils/UUPSUpgradeable.sol",
        "@openzeppelin/contracts-upgradeable/utils/ReentrancyGuardUpgradeable.sol",
        "@openzeppelin/contracts-upgradeable/utils/PausableUpgradeable.sol",
        "./PrizeStorage.sol"
      ],
      "versionPragmas": [
        "^0.8.22"
      ],
      "artifacts": [
        "PrizeDistributor"
      ]
    },
    "/Users/admin/social-points/node_modules/@openzeppelin/contracts-upgradeable/access/OwnableUpgradeable.sol": {
      "lastModificationDate": 1730103621096,
      "contentHash": "77d30f3cd93f46b80b6f8f1ebc574ee4",
      "sourceName": "@openzeppelin/contracts-upgradeable/access/OwnableUpgradeable.sol",
      "solcConfig": {
        "version": "0.8.22",
        "settings": {
          "optimizer": {
            "enabled": true,
            "runs": 200
          },
          "viaIR": true,
          "evmVersion": "paris",
          "outputSelection": {
            "*": {
              "*": [
                "abi",
                "evm.bytecode",
                "evm.deployedBytecode",
                "evm.methodIdentifiers",
                "metadata",
                "storageLayout"
              ],
              "": [
                "ast"
              ]
            }
          }
        }
      },
      "imports": [
        "../utils/ContextUpgradeable.sol",
        "../proxy/utils/Initializable.sol"
      ],
      "versionPragmas": [
        "^0.8.20"
      ],
      "artifacts": [
        "OwnableUpgradeable"
      ]
    },
    "/Users/admin/social-points/node_modules/@openzeppelin/contracts-upgradeable/utils/ReentrancyGuardUpgradeable.sol": {
      "lastModificationDate": 1730103621097,
      "contentHash": "24562076b21756e3358ede5e844008ce",
      "sourceName": "@openzeppelin/contracts-upgradeable/utils/ReentrancyGuardUpgradeable.sol",
      "solcConfig": {
        "version": "0.8.22",
        "settings": {
          "optimizer": {
            "enabled": true,
            "runs": 200
          },
          "viaIR": true,
          "evmVersion": "paris",
          "outputSelection": {
            "*": {
              "*": [
                "abi",
                "evm.bytecode",
                "evm.deployedBytecode",
                "evm.methodIdentifiers",
                "metadata",
                "storageLayout"
              ],
              "": [
                "ast"
              ]
            }
          }
        }
      },
      "imports": [
        "../proxy/utils/Initializable.sol"
      ],
      "versionPragmas": [
        "^0.8.20"
      ],
      "artifacts": [
        "ReentrancyGuardUpgradeable"
      ]
    },
    "/Users/admin/social-points/node_modules/@openzeppelin/contracts-upgradeable/utils/PausableUpgradeable.sol": {
      "lastModificationDate": 1730103621096,
      "contentHash": "ef20fd32f5bdcc50bd466abc8fc7f181",
      "sourceName": "@openzeppelin/contracts-upgradeable/utils/PausableUpgradeable.sol",
      "solcConfig": {
        "version": "0.8.22",
        "settings": {
          "optimizer": {
            "enabled": true,
            "runs": 200
          },
          "viaIR": true,
          "evmVersion": "paris",
          "outputSelection": {
            "*": {
              "*": [
                "abi",
                "evm.bytecode",
                "evm.deployedBytecode",
                "evm.methodIdentifiers",
                "metadata",
                "storageLayout"
              ],
              "": [
                "ast"
              ]
            }
          }
        }
      },
      "imports": [
        "../utils/ContextUpgradeable.sol",
        "../proxy/utils/Initializable.sol"
      ],
      "versionPragmas": [
        "^0.8.20"
      ],
      "artifacts": [
        "PausableUpgradeable"
      ]
    },
    "/Users/admin/social-points/node_modules/@openzeppelin/contracts-upgradeable/proxy/utils/Initializable.sol": {
      "lastModificationDate": 1730103621095,
      "contentHash": "f0cedd674b4863ee90d1521a92ab82df",
      "sourceName": "@openzeppelin/contracts-upgradeable/proxy/utils/Initializable.sol",
      "solcConfig": {
        "version": "0.8.22",
        "settings": {
          "optimizer": {
            "enabled": true,
            "runs": 200
          },
          "viaIR": true,
          "evmVersion": "paris",
          "outputSelection": {
            "*": {
              "*": [
                "abi",
                "evm.bytecode",
                "evm.deployedBytecode",
                "evm.methodIdentifiers",
                "metadata",
                "storageLayout"
              ],
              "": [
                "ast"
              ]
            }
          }
        }
      },
      "imports": [],
      "versionPragmas": [
        "^0.8.20"
      ],
      "artifacts": [
        "Initializable"
      ]
    },
    "/Users/admin/social-points/node_modules/@openzeppelin/contracts-upgradeable/proxy/utils/UUPSUpgradeable.sol": {
      "lastModificationDate": 1730103621099,
      "contentHash": "3dff09f84f7ddc1e57683d134b53617f",
      "sourceName": "@openzeppelin/contracts-upgradeable/proxy/utils/UUPSUpgradeable.sol",
      "solcConfig": {
        "version": "0.8.22",
        "settings": {
          "optimizer": {
            "enabled": true,
            "runs": 200
          },
          "viaIR": true,
          "evmVersion": "paris",
          "outputSelection": {
            "*": {
              "*": [
                "abi",
                "evm.bytecode",
                "evm.deployedBytecode",
                "evm.methodIdentifiers",
                "metadata",
                "storageLayout"
              ],
              "": [
                "ast"
              ]
            }
          }
        }
      },
      "imports": [
        "@openzeppelin/contracts/interfaces/draft-IERC1822.sol",
        "@openzeppelin/contracts/proxy/ERC1967/ERC1967Utils.sol",
        "./Initializable.sol"
      ],
      "versionPragmas": [
        "^0.8.20"
      ],
      "artifacts": [
        "UUPSUpgradeable"
      ]
    },
    "/Users/admin/social-points/contracts/PlayerScoring.sol": {
      "lastModificationDate": 1730107557150,
      "contentHash": "b6a9bfa0bb2a9fe561e596d5e6be976c",
      "sourceName": "contracts/PlayerScoring.sol",
      "solcConfig": {
        "version": "0.8.22",
        "settings": {
          "optimizer": {
            "enabled": true,
            "runs": 200
          },
          "viaIR": true,
          "evmVersion": "paris",
          "outputSelection": {
            "*": {
              "*": [
                "abi",
                "evm.bytecode",
                "evm.deployedBytecode",
                "evm.methodIdentifiers",
                "metadata",
                "storageLayout"
              ],
              "": [
                "ast"
              ]
            }
          }
        }
      },
      "imports": [
        "@openzeppelin/contracts-upgradeable/proxy/utils/Initializable.sol",
        "@openzeppelin/contracts-upgradeable/access/OwnableUpgradeable.sol",
        "@openzeppelin/contracts-upgradeable/proxy/utils/UUPSUpgradeable.sol"
      ],
      "versionPragmas": [
        "^0.8.22"
      ],
      "artifacts": [
        "PlayerScoring"
      ]
    },
    "/Users/admin/social-points/node_modules/@openzeppelin/contracts-upgradeable/utils/ContextUpgradeable.sol": {
      "lastModificationDate": 1730103621059,
      "contentHash": "c28aaa25d083a9a55bd9ec9e0b785122",
      "sourceName": "@openzeppelin/contracts-upgradeable/utils/ContextUpgradeable.sol",
      "solcConfig": {
        "version": "0.8.22",
        "settings": {
          "optimizer": {
            "enabled": true,
            "runs": 200
          },
          "viaIR": true,
          "evmVersion": "paris",
          "outputSelection": {
            "*": {
              "*": [
                "abi",
                "evm.bytecode",
                "evm.deployedBytecode",
                "evm.methodIdentifiers",
                "metadata",
                "storageLayout"
              ],
              "": [
                "ast"
              ]
            }
          }
        }
      },
      "imports": [
        "../proxy/utils/Initializable.sol"
      ],
      "versionPragmas": [
        "^0.8.20"
      ],
      "artifacts": [
        "ContextUpgradeable"
      ]
    },
    "/Users/admin/social-points/node_modules/@openzeppelin/contracts/proxy/ERC1967/ERC1967Utils.sol": {
      "lastModificationDate": 1730103621104,
      "contentHash": "405dda10d03b5eabd05700d23cc601ec",
      "sourceName": "@openzeppelin/contracts/proxy/ERC1967/ERC1967Utils.sol",
      "solcConfig": {
        "version": "0.8.22",
        "settings": {
          "optimizer": {
            "enabled": true,
            "runs": 200
          },
          "viaIR": true,
          "evmVersion": "paris",
          "outputSelection": {
            "*": {
              "*": [
                "abi",
                "evm.bytecode",
                "evm.deployedBytecode",
                "evm.methodIdentifiers",
                "metadata",
                "storageLayout"
              ],
              "": [
                "ast"
              ]
            }
          }
        }
      },
      "imports": [
        "../beacon/IBeacon.sol",
        "../../interfaces/IERC1967.sol",
        "../../utils/Address.sol",
        "../../utils/StorageSlot.sol"
      ],
      "versionPragmas": [
        "^0.8.21"
      ],
      "artifacts": [
        "ERC1967Utils"
      ]
    },
    "/Users/admin/social-points/node_modules/@openzeppelin/contracts/interfaces/draft-IERC1822.sol": {
      "lastModificationDate": 1730103621092,
      "contentHash": "64a2b7a96950f0641c477993f3029477",
      "sourceName": "@openzeppelin/contracts/interfaces/draft-IERC1822.sol",
      "solcConfig": {
        "version": "0.8.22",
        "settings": {
          "optimizer": {
            "enabled": true,
            "runs": 200
          },
          "viaIR": true,
          "evmVersion": "paris",
          "outputSelection": {
            "*": {
              "*": [
                "abi",
                "evm.bytecode",
                "evm.deployedBytecode",
                "evm.methodIdentifiers",
                "metadata",
                "storageLayout"
              ],
              "": [
                "ast"
              ]
            }
          }
        }
      },
      "imports": [],
      "versionPragmas": [
        "^0.8.20"
      ],
      "artifacts": [
        "IERC1822Proxiable"
      ]
    },
    "/Users/admin/social-points/node_modules/@openzeppelin/contracts/interfaces/IERC1967.sol": {
      "lastModificationDate": 1730103621126,
      "contentHash": "4e17c826a54a8ee1a185449d4695d07d",
      "sourceName": "@openzeppelin/contracts/interfaces/IERC1967.sol",
      "solcConfig": {
        "version": "0.8.22",
        "settings": {
          "optimizer": {
            "enabled": true,
            "runs": 200
          },
          "viaIR": true,
          "evmVersion": "paris",
          "outputSelection": {
            "*": {
              "*": [
                "abi",
                "evm.bytecode",
                "evm.deployedBytecode",
                "evm.methodIdentifiers",
                "metadata",
                "storageLayout"
              ],
              "": [
                "ast"
              ]
            }
          }
        }
      },
      "imports": [],
      "versionPragmas": [
        "^0.8.20"
      ],
      "artifacts": [
        "IERC1967"
      ]
    },
    "/Users/admin/social-points/node_modules/@openzeppelin/contracts/utils/Address.sol": {
      "lastModificationDate": 1730103621082,
      "contentHash": "553fc9ae17d9c00fd1c301b760781e26",
      "sourceName": "@openzeppelin/contracts/utils/Address.sol",
      "solcConfig": {
        "version": "0.8.22",
        "settings": {
          "optimizer": {
            "enabled": true,
            "runs": 200
          },
          "viaIR": true,
          "evmVersion": "paris",
          "outputSelection": {
            "*": {
              "*": [
                "abi",
                "evm.bytecode",
                "evm.deployedBytecode",
                "evm.methodIdentifiers",
                "metadata",
                "storageLayout"
              ],
              "": [
                "ast"
              ]
            }
          }
        }
      },
      "imports": [
        "./Errors.sol"
      ],
      "versionPragmas": [
        "^0.8.20"
      ],
      "artifacts": [
        "Address"
      ]
    },
    "/Users/admin/social-points/node_modules/@openzeppelin/contracts/utils/StorageSlot.sol": {
      "lastModificationDate": 1730103621142,
      "contentHash": "e656d64c4ce918f3d13030b91c935134",
      "sourceName": "@openzeppelin/contracts/utils/StorageSlot.sol",
      "solcConfig": {
        "version": "0.8.22",
        "settings": {
          "optimizer": {
            "enabled": true,
            "runs": 200
          },
          "viaIR": true,
          "evmVersion": "paris",
          "outputSelection": {
            "*": {
              "*": [
                "abi",
                "evm.bytecode",
                "evm.deployedBytecode",
                "evm.methodIdentifiers",
                "metadata",
                "storageLayout"
              ],
              "": [
                "ast"
              ]
            }
          }
        }
      },
      "imports": [],
      "versionPragmas": [
        "^0.8.20"
      ],
      "artifacts": [
        "StorageSlot"
      ]
    },
    "/Users/admin/social-points/node_modules/@openzeppelin/contracts/proxy/beacon/IBeacon.sol": {
      "lastModificationDate": 1730103621121,
      "contentHash": "0a5c323fd908535580597848b8e550fb",
      "sourceName": "@openzeppelin/contracts/proxy/beacon/IBeacon.sol",
      "solcConfig": {
        "version": "0.8.22",
        "settings": {
          "optimizer": {
            "enabled": true,
            "runs": 200
          },
          "viaIR": true,
          "evmVersion": "paris",
          "outputSelection": {
            "*": {
              "*": [
                "abi",
                "evm.bytecode",
                "evm.deployedBytecode",
                "evm.methodIdentifiers",
                "metadata",
                "storageLayout"
              ],
              "": [
                "ast"
              ]
            }
          }
        }
      },
      "imports": [],
      "versionPragmas": [
        "^0.8.20"
      ],
      "artifacts": [
        "IBeacon"
      ]
    },
    "/Users/admin/social-points/node_modules/@openzeppelin/contracts/utils/Errors.sol": {
      "lastModificationDate": 1730103621113,
      "contentHash": "6b5eac2b85500c3012977849cfd633d8",
      "sourceName": "@openzeppelin/contracts/utils/Errors.sol",
      "solcConfig": {
        "version": "0.8.22",
        "settings": {
          "optimizer": {
            "enabled": true,
            "runs": 200
          },
          "viaIR": true,
          "evmVersion": "paris",
          "outputSelection": {
            "*": {
              "*": [
                "abi",
                "evm.bytecode",
                "evm.deployedBytecode",
                "evm.methodIdentifiers",
                "metadata",
                "storageLayout"
              ],
              "": [
                "ast"
              ]
            }
          }
        }
      },
      "imports": [],
      "versionPragmas": [
        "^0.8.20"
      ],
      "artifacts": [
        "Errors"
      ]
    },
    "/Users/admin/social-points/contracts/PointsRules.sol": {
      "lastModificationDate": 1730107564112,
      "contentHash": "ec6a826e04714eb1d29d5d34994118bd",
      "sourceName": "contracts/PointsRules.sol",
      "solcConfig": {
        "version": "0.8.22",
        "settings": {
          "optimizer": {
            "enabled": true,
            "runs": 200
          },
          "viaIR": true,
          "evmVersion": "paris",
          "outputSelection": {
            "*": {
              "*": [
                "abi",
                "evm.bytecode",
                "evm.deployedBytecode",
                "evm.methodIdentifiers",
                "metadata",
                "storageLayout"
              ],
              "": [
                "ast"
              ]
            }
          }
        }
      },
      "imports": [
        "@openzeppelin/contracts-upgradeable/proxy/utils/Initializable.sol",
        "@openzeppelin/contracts-upgradeable/access/OwnableUpgradeable.sol",
        "@openzeppelin/contracts-upgradeable/proxy/utils/UUPSUpgradeable.sol"
      ],
      "versionPragmas": [
        "^0.8.22"
      ],
      "artifacts": [
        "PointsRules"
      ]
    },
    "/Users/admin/social-points/contracts/PrizeStorage.sol": {
      "lastModificationDate": 1730107524029,
      "contentHash": "c9d5cfaadedada50bc6652693a5bc7a3",
      "sourceName": "contracts/PrizeStorage.sol",
      "solcConfig": {
        "version": "0.8.22",
        "settings": {
          "optimizer": {
            "enabled": true,
            "runs": 200
          },
          "viaIR": true,
          "evmVersion": "paris",
          "outputSelection": {
            "*": {
              "*": [
                "abi",
                "evm.bytecode",
                "evm.deployedBytecode",
                "evm.methodIdentifiers",
                "metadata",
                "storageLayout"
              ],
              "": [
                "ast"
              ]
            }
          }
        }
      },
      "imports": [
        "@openzeppelin/contracts-upgradeable/proxy/utils/Initializable.sol",
        "@openzeppelin/contracts-upgradeable/access/OwnableUpgradeable.sol",
        "@openzeppelin/contracts-upgradeable/proxy/utils/UUPSUpgradeable.sol"
      ],
      "versionPragmas": [
        "^0.8.22"
      ],
      "artifacts": [
        "PrizeStorage"
      ]
    },
    "/Users/admin/social-points/contracts/GameFactory.sol": {
      "lastModificationDate": 1730224727786,
      "contentHash": "6b7c8c774de322a04236fffc1f2f21cf",
      "sourceName": "contracts/GameFactory.sol",
      "solcConfig": {
        "version": "0.8.22",
        "settings": {
          "optimizer": {
            "enabled": true,
            "runs": 200
          },
          "viaIR": true,
          "evmVersion": "paris",
          "outputSelection": {
            "*": {
              "*": [
                "abi",
                "evm.bytecode",
                "evm.deployedBytecode",
                "evm.methodIdentifiers",
                "metadata",
                "storageLayout"
              ],
              "": [
                "ast"
              ]
            }
          }
        }
      },
      "imports": [
        "@openzeppelin/contracts-upgradeable/proxy/utils/Initializable.sol",
        "@openzeppelin/contracts-upgradeable/access/OwnableUpgradeable.sol",
        "@openzeppelin/contracts-upgradeable/proxy/utils/UUPSUpgradeable.sol",
        "@openzeppelin/contracts-upgradeable/utils/PausableUpgradeable.sol",
        "./Game.sol"
      ],
      "versionPragmas": [
        "^0.8.22"
      ],
      "artifacts": [
        "GameFactory"
      ]
    },
    "/Users/admin/social-points/contracts/storage/GameStorage.sol": {
      "lastModificationDate": 1730108406684,
      "contentHash": "1f527778d4c186406e59c3bc5e632f52",
      "sourceName": "contracts/storage/GameStorage.sol",
      "solcConfig": {
        "version": "0.8.22",
        "settings": {
          "optimizer": {
            "enabled": true,
            "runs": 200
          },
          "viaIR": true,
          "evmVersion": "paris",
          "outputSelection": {
            "*": {
              "*": [
                "abi",
                "evm.bytecode",
                "evm.deployedBytecode",
                "evm.methodIdentifiers",
                "metadata",
                "storageLayout"
              ],
              "": [
                "ast"
              ]
            }
          }
        }
      },
      "imports": [],
      "versionPragmas": [
        "^0.8.22"
      ],
      "artifacts": [
        "GameStorage"
      ]
    },
    "/Users/admin/social-points/contracts/libraries/GameLibrary.sol": {
      "lastModificationDate": 1730150349265,
      "contentHash": "0f685dc3a18f73b9632cfcc2a3855d82",
      "sourceName": "contracts/libraries/GameLibrary.sol",
      "solcConfig": {
        "version": "0.8.22",
        "settings": {
          "optimizer": {
            "enabled": true,
            "runs": 200
          },
          "viaIR": true,
          "evmVersion": "paris",
          "outputSelection": {
            "*": {
              "*": [
                "abi",
                "evm.bytecode",
                "evm.deployedBytecode",
                "evm.methodIdentifiers",
                "metadata",
                "storageLayout"
              ],
              "": [
                "ast"
              ]
            }
          }
        }
      },
      "imports": [],
      "versionPragmas": [
        "^0.8.22"
      ],
      "artifacts": [
        "GameLibrary"
      ]
    },
    "/Users/admin/social-points/contracts/PointsSystem.sol": {
      "lastModificationDate": 1730108520356,
      "contentHash": "7ee58f91f249773e523e9a2d51009ff4",
      "sourceName": "contracts/PointsSystem.sol",
      "solcConfig": {
        "version": "0.8.22",
        "settings": {
          "optimizer": {
            "enabled": true,
            "runs": 200
          },
          "viaIR": true,
          "evmVersion": "paris",
          "outputSelection": {
            "*": {
              "*": [
                "abi",
                "evm.bytecode",
                "evm.deployedBytecode",
                "evm.methodIdentifiers",
                "metadata",
                "storageLayout"
              ],
              "": [
                "ast"
              ]
            }
          }
        }
      },
      "imports": [
        "./libraries/GameLibrary.sol",
        "./storage/GameStorage.sol",
        "@openzeppelin/contracts-upgradeable/proxy/utils/UUPSUpgradeable.sol"
      ],
      "versionPragmas": [
        "^0.8.22"
      ],
      "artifacts": [
        "PointsSystem"
      ]
    },
    "/Users/admin/social-points/contracts/libraries/GameErrors.sol": {
      "lastModificationDate": 1730108052838,
      "contentHash": "17c6c5ae430cb627a79efc05719f15af",
      "sourceName": "contracts/libraries/GameErrors.sol",
      "solcConfig": {
        "version": "0.8.22",
        "settings": {
          "optimizer": {
            "enabled": true,
            "runs": 200
          },
          "viaIR": true,
          "evmVersion": "paris",
          "outputSelection": {
            "*": {
              "*": [
                "abi",
                "evm.bytecode",
                "evm.deployedBytecode",
                "evm.methodIdentifiers",
                "metadata",
                "storageLayout"
              ],
              "": [
                "ast"
              ]
            }
          }
        }
      },
      "imports": [],
      "versionPragmas": [
        "^0.8.22"
      ],
      "artifacts": [
        "GameErrors"
      ]
    },
    "/Users/admin/social-points/contracts/libraries/GameLogic.sol": {
      "lastModificationDate": 1730108399277,
      "contentHash": "b05d9a01faf4e979a41e18a52af0423f",
      "sourceName": "contracts/libraries/GameLogic.sol",
      "solcConfig": {
        "version": "0.8.22",
        "settings": {
          "optimizer": {
            "enabled": true,
            "runs": 200
          },
          "viaIR": true,
          "evmVersion": "paris",
          "outputSelection": {
            "*": {
              "*": [
                "abi",
                "evm.bytecode",
                "evm.deployedBytecode",
                "evm.methodIdentifiers",
                "metadata",
                "storageLayout"
              ],
              "": [
                "ast"
              ]
            }
          }
        }
      },
      "imports": [
        "./GameTypes.sol"
      ],
      "versionPragmas": [
        "^0.8.22"
      ],
      "artifacts": [
        "GameLogic"
      ]
    },
    "/Users/admin/social-points/contracts/libraries/GameTypes.sol": {
      "lastModificationDate": 1730208591377,
      "contentHash": "16138d42daa0b549b0924c8723071ec9",
      "sourceName": "contracts/libraries/GameTypes.sol",
      "solcConfig": {
        "version": "0.8.22",
        "settings": {
          "optimizer": {
            "enabled": true,
            "runs": 200
          },
          "viaIR": true,
          "evmVersion": "paris",
          "outputSelection": {
            "*": {
              "*": [
                "abi",
                "evm.bytecode",
                "evm.deployedBytecode",
                "evm.methodIdentifiers",
                "metadata",
                "storageLayout"
              ],
              "": [
                "ast"
              ]
            }
          }
        }
      },
      "imports": [],
      "versionPragmas": [
        "^0.8.22"
      ],
      "artifacts": [
        "GameTypes"
      ]
    },
    "/Users/admin/social-points/contracts/libraries/GameUtils.sol": {
      "lastModificationDate": 1730108039018,
      "contentHash": "e16abf315bfc706cce5662654a55b01f",
      "sourceName": "contracts/libraries/GameUtils.sol",
      "solcConfig": {
        "version": "0.8.22",
        "settings": {
          "optimizer": {
            "enabled": true,
            "runs": 200
          },
          "viaIR": true,
          "evmVersion": "paris",
          "outputSelection": {
            "*": {
              "*": [
                "abi",
                "evm.bytecode",
                "evm.deployedBytecode",
                "evm.methodIdentifiers",
                "metadata",
                "storageLayout"
              ],
              "": [
                "ast"
              ]
            }
          }
        }
      },
      "imports": [],
      "versionPragmas": [
        "^0.8.22"
      ],
      "artifacts": [
        "GameUtils"
      ]
    },
    "/Users/admin/social-points/contracts/libraries/SortingUtils.sol": {
      "lastModificationDate": 1730108701697,
      "contentHash": "7371ae5f2d667d334d569247fc6d83de",
      "sourceName": "contracts/libraries/SortingUtils.sol",
      "solcConfig": {
        "version": "0.8.22",
        "settings": {
          "optimizer": {
            "enabled": true,
            "runs": 200
          },
          "viaIR": true,
          "evmVersion": "paris",
          "outputSelection": {
            "*": {
              "*": [
                "abi",
                "evm.bytecode",
                "evm.deployedBytecode",
                "evm.methodIdentifiers",
                "metadata",
                "storageLayout"
              ],
              "": [
                "ast"
              ]
            }
          }
        }
      },
      "imports": [],
      "versionPragmas": [
        "^0.8.22"
      ],
      "artifacts": [
        "SortingUtils"
      ]
    }
  }
}
